.coveragerc
.gitignore
.gitmodules
BUILD.bazel
CMakeLists.txt
CMakeLists.txt.gtest.in
LICENSE
MANIFEST.in
README.md
README.pypi
WORKSPACE
appveyor.yml
deps.bzl
package.json
pytest.ini
requirements.txt
setup.cfg
setup.py
test-requirements.txt
versioneer.py
.circleci/bash_env.sh
.circleci/build_emscripten.sh
.circleci/config.yml
.circleci/install_node.sh
deps/.gitkeep
deps/PicoSHA2/.git
deps/PicoSHA2/LICENSE
deps/PicoSHA2/README.md
deps/PicoSHA2/picosha2.h
deps/PicoSHA2/example/hasher.cpp
deps/PicoSHA2/example/interactive_hasher.cpp
deps/PicoSHA2/test/test.cpp
deps/dilithium/.git
deps/dilithium/.travis.yml
deps/dilithium/AUTHORS.md
deps/dilithium/README.md
deps/dilithium/avx2/Makefile
deps/dilithium/avx2/PQCgenKAT_sign.c
deps/dilithium/avx2/api.h
deps/dilithium/avx2/consts.c
deps/dilithium/avx2/fips202.c
deps/dilithium/avx2/fips202.h
deps/dilithium/avx2/fips202x4.c
deps/dilithium/avx2/fips202x4.h
deps/dilithium/avx2/invntt.s
deps/dilithium/avx2/ntt.h
deps/dilithium/avx2/ntt.s
deps/dilithium/avx2/packing.c
deps/dilithium/avx2/packing.h
deps/dilithium/avx2/params.h
deps/dilithium/avx2/pointwise_mul.s
deps/dilithium/avx2/poly.c
deps/dilithium/avx2/poly.h
deps/dilithium/avx2/polyvec.c
deps/dilithium/avx2/polyvec.h
deps/dilithium/avx2/randombytes.c
deps/dilithium/avx2/randombytes.h
deps/dilithium/avx2/reduce.c
deps/dilithium/avx2/reduce.h
deps/dilithium/avx2/rng.c
deps/dilithium/avx2/rng.h
deps/dilithium/avx2/rounding.c
deps/dilithium/avx2/rounding.h
deps/dilithium/avx2/sign.c
deps/dilithium/avx2/sign.h
deps/dilithium/avx2/keccak4x/KeccakP-1600-times4-SIMD256.c
deps/dilithium/avx2/keccak4x/KeccakP-1600-times4-SnP.h
deps/dilithium/avx2/keccak4x/KeccakP-1600-unrolling.macros
deps/dilithium/avx2/keccak4x/SIMD256-config.h
deps/dilithium/avx2/keccak4x/align.h
deps/dilithium/avx2/keccak4x/brg_endian.h
deps/dilithium/avx2/test/cpucycles.c
deps/dilithium/avx2/test/cpucycles.h
deps/dilithium/avx2/test/speed.c
deps/dilithium/avx2/test/speed.h
pyqrllib.egg-info/PKG-INFO
pyqrllib.egg-info/SOURCES.txt
pyqrllib.egg-info/dependency_links.txt
pyqrllib.egg-info/top_level.txt
