Metadata-Version: 1.1
Name: pyqrllib
Version: 1.2.3
Summary: QRL core library
Home-page: http://theqrl.org
Author: The Quantum Resistant Ledger
Author-email: info@theQRL.org
License: MIT
Platform: UNKNOWN
Classifier: Development Status :: 3 - Alpha
Classifier: Programming Language :: Python
Classifier: Programming Language :: Python :: 3
Classifier: Programming Language :: Python :: 3.5
